LICENSE
MANIFEST.in
README.rst
setup.py
djangogenerics/__init__.py
djangogenerics/filters.py
djangogenerics/forms.py
djangogenerics/http.py
djangogenerics/middleware.py
djangogenerics/models.py
djangogenerics/widgets.py
djangogenerics.egg-info/PKG-INFO
djangogenerics.egg-info/SOURCES.txt
djangogenerics.egg-info/dependency_links.txt
djangogenerics.egg-info/not-zip-safe
djangogenerics.egg-info/top_level.txt
djangogenerics/dropbox/__init__.py
djangogenerics/dropbox/backends.py
djangogenerics/dropbox/session.py
djangogenerics/static/djangogenerics/js/ForeignKeyAutoCompleteWidget.js
djangogenerics/static/djangogenerics/js/MassActions.js
djangogenerics/static/djangogenerics/js/SimpleChoiceFilter.js
djangogenerics/static/djangogenerics/js/tags_autocomplete_widget.js
djangogenerics/taggit/__init__.py
djangogenerics/view/__init__.py
djangogenerics/view/mixins.py