Metadata-Version: 1.0
Name: djangogenerics
Version: 0.5.6
Summary: A collection of Django 1.5+ utilities
Home-page: http://nrocco.github.io/
Author: Nico Di Rocco
Author-email: dirocco.nico@gmail.com
License: Copyright (c) 2013, Nico Di Rocco.
